ai_coach/__init__.py
ai_coach/ai_coach.py
ai_coach/static/README.txt
ai_coach/static/css/ai_coach.css
ai_coach/static/html/ai_coach.html
ai_coach/static/js/src/ai_coach.js
ai_coach_xblock-1.1.0.dist-info/LICENSE
ai_coach_xblock-1.1.0.dist-info/METADATA
ai_coach_xblock-1.1.0.dist-info/WHEEL
ai_coach_xblock-1.1.0.dist-info/entry_points.txt
ai_coach_xblock-1.1.0.dist-info/top_level.txt
ai_coach_xblock-1.1.0.dist-info/RECORD
