Metadata-Version: 2.2
Name: ai-coach-xblock
Version: 1.1.0
Summary: AI Coach Xblock evaluates open response answer of a question using Open AI
Home-page: https://github.com/edly-io/ai-coach-xblock
Author: edly
License: AGPL v3
License-File: LICENSE
Requires-Dist: XBlock
Requires-Dist: xblock-utils
Requires-Dist: openai==1.65.1
Dynamic: author
Dynamic: description
Dynamic: description-content-type
Dynamic: home-page
Dynamic: license
Dynamic: requires-dist
Dynamic: summary
